stupidgen/__init__.py
stupidgen/__main__.py
stupidgen/basichandlers.py
stupidgen/languages.py
stupidgen/processor.py
stupidgen/stringprocessing.py
stupidgen-0.3.0.dist-info/LICENSE
stupidgen-0.3.0.dist-info/METADATA
stupidgen-0.3.0.dist-info/WHEEL
stupidgen-0.3.0.dist-info/entry_points.txt
stupidgen-0.3.0.dist-info/top_level.txt
stupidgen-0.3.0.dist-info/RECORD
