Metadata-Version: 2.1
Name: stupidgen
Version: 0.3.0
Summary: Generate text document from simple scripts using your favorite language.
Home-page: https://framagit.org/squirrrr/stupidgen
Author: Marc Heinrich
Author-email: marc.heinrich@free.fr
License: GNU General Public License v3
Keywords: stupidgen
Classifier: Development Status :: 2 - Pre-Alpha
Classifier: Intended Audience :: Developers
Classifier: Environment :: Console
Classifier: License :: OSI Approved :: GNU General Public License v3 (GPLv3)
Classifier: Programming Language :: Python :: 3
Classifier: Programming Language :: Python :: 3.6
Classifier: Programming Language :: Python :: 3.7
Classifier: Programming Language :: Python :: 3.8
Classifier: Operating System :: MacOS
Classifier: Operating System :: Microsoft :: Windows
Classifier: Operating System :: POSIX
Classifier: Topic :: Software Development :: Code Generators
Provides: s
Provides: t
Provides: u
Provides: p
Provides: i
Provides: d
Provides: g
Provides: e
Provides: n
Requires-Python: >=3.6
License-File: LICENSE
